[
  {
    "id": 1,
    "orderNum": "11",
    "orderDate": "2022-04-18 18:33",
    "title": "상품이름",
    "orderPicture": "/images/people.jpg" ,
    "orderQuantity": 1,
    "orderPrice": 2200.0,
    "addOn": [
          {
          "packaging":"포장여부:포장"
        }
    ],
    "orderCondition":"입금대기",
    "orderShipping": "무료",
    "orderInfo": "3213/2321312312",
    "orderAddress":"대전 동구 머시기 머시기 머시기",
    "orderZipcode":"우)12312",
    "paymentMethod":"무통장입금",
    "orderBank":"신한(123)"
  },
  {
    "id": 2,
    "orderNum": "11",
    "orderDate": "2022-04-18 18:33",
    "title": "상품이름",
    "orderPicture": "/images/people.jpg" ,
    "orderQuantity": 3,
    "orderPrice": 13000.0,
    "addOn": [
          {
          "addOn":"악세서리:펜",
          "packaging":"포장여부:포장"
        }
    ],
    "orderCondition":"입금대기",
    "orderShipping": "무료",
    "orderInfo": "3213/2321312312",
    "orderAddress":"대전 동구 머시기 머시기 머시기",
    "orderZipcode":"우)12312",
    "paymentMethod":"무통장입금",
    "orderBank":"신한(123)"
  },
  {
    "id": 3,
    "orderNum": "3",
    "orderDate": "2022-04-18 18:33",
    "title": "상품이름",
    "orderPicture": "/images/people.jpg" ,
    "orderQuantity": 3,
    "orderPrice": 200000.0,
    "addOn": [
          {
          "color":"색상:빨강",
          "addOn":"악세서리:펜",
          "packaging":"포장여부:포장"
        }
    ],
    "orderCondition":"입금완료",
    "orderShipping": 2400,
    "orderInfo": "3213/2321312312",
    "orderAddress":"대전 동구 머시기 머시기 머시기",
    "orderZipcode":"우)12312",
    "paymentMethod":"계좌이체",
    "orderBank":"신한(123)"
  }
]